artemis_model/__init__.py
artemis_model/album.py
artemis_model/approved_playlist_list.py
artemis_model/artist.py
artemis_model/auth.py
artemis_model/banned_tracks.py
artemis_model/base.py
artemis_model/billing.py
artemis_model/category.py
artemis_model/dj_set.py
artemis_model/genre.py
artemis_model/location.py
artemis_model/location_genre_exclusion.py
artemis_model/message.py
artemis_model/organization.py
artemis_model/organization_include_pal_setting.py
artemis_model/otp.py
artemis_model/permission.py
artemis_model/playlist.py
artemis_model/redis/__init__.py
artemis_model/redis/bucket.py
artemis_model/redis/device.py
artemis_model/redis/keys.py
artemis_model/redis/play_history.py
artemis_model/redis/zone_state.py
artemis_model/schedule.py
artemis_model/setting.py
artemis_model/sqs/__init__.py
artemis_model/sqs/messages.py
artemis_model/sync_state.py
artemis_model/track.py
artemis_model/user.py
artemis_model/zone.py
artemis_model/zone_activity.py
artemis_model/zone_state.py
artemis_model-0.1.300.dist-info/METADATA
artemis_model-0.1.300.dist-info/WHEEL
artemis_model-0.1.300.dist-info/RECORD
