Metadata-Version: 2.4
Name: artemis-model
Version: 0.1.300
Summary: 
Author: Jukeboxy
Requires-Python: >=3.10.6,<4.0.0
Classifier: Programming Language :: Python :: 3
Classifier: Programming Language :: Python :: 3.11
Classifier: Programming Language :: Python :: 3.12
Classifier: Programming Language :: Python :: 3.13
Classifier: Programming Language :: Python :: 3.14
Requires-Dist: alembic (>=1.13.1,<2.0.0)
Requires-Dist: asyncpg (>=0.30.0,<0.31.0)
Requires-Dist: boto3 (>=1.34.0,<2.0.0)
Requires-Dist: greenlet (>=3.0.2,<4.0.0)
Requires-Dist: pydantic (>=2.10.2,<3.0.0)
Requires-Dist: python-dotenv (>=1.0.0,<2.0.0)
Requires-Dist: python-slugify (>=8.0.4,<9.0.0)
Requires-Dist: sqlalchemy (>=2.0.23,<3.0.0)
